{
  "kind": "collectionType",
  "collectionName": "list_offer_services",
  "info": {
    "singularName": "list-offer-service",
    "pluralName": "list-offer-services",
    "displayName": "ListOfferService"
  },
  "options": {
    "draftAndPublish": true
  },
  "pluginOptions": {},
  "attributes": {
    "item": {
      "type": "text"
    },
    "we_offer_service": {
      "type": "relation",
      "relation": "manyToOne",
      "target": "api::we-offer-service.we-offer-service",
      "inversedBy": "list_offer_services"
    }
  }
}
